radix_mlp-0.0.1.dist-info/METADATA
radix_mlp-0.0.1.dist-info/WHEEL
radix_mlp.libs/libgcc_s-f5fcfe20.so.1
radix_mlp/__init__.py
radix_mlp/_core.abi3.so
radix_mlp/py.typed
radix_mlp/torch.py
radix_mlp-0.0.1.dist-info/RECORD
