Metadata-Version: 2.4
Name: radix-mlp
Version: 0.0.1
Classifier: Development Status :: 3 - Alpha
Classifier: Intended Audience :: Developers
Classifier: License :: OSI Approved :: MIT License
Classifier: Programming Language :: Python :: 3
Classifier: Programming Language :: Python :: 3.10
Classifier: Programming Language :: Python :: 3.11
Classifier: Programming Language :: Python :: 3.12
Classifier: Programming Language :: Python :: 3.13
Classifier: Programming Language :: Python :: 3.14
Classifier: Programming Language :: Rust
Classifier: Topic :: Scientific/Engineering :: Artificial Intelligence
Requires-Dist: numpy>=1
Requires-Dist: pytest>=7 ; extra == 'dev'
Requires-Dist: torch>=2.0 ; extra == 'dev'
Provides-Extra: dev
Summary: RadixMLP: Prefix-based computation sharing for transformer models
Keywords: transformers,optimization,radix,mlp
Author-email: Michael Feil <no-reply@michaelfeil.eu>
License: MIT
Requires-Python: >=3.10
